django_smtp_ntlm_backend/__init__.py
django_smtp_ntlm_backend/models.py
django_smtp_ntlm_backend/settings.py
django_smtp_ntlm_backend/tests.py
django_smtp_ntlm_backend-0.0.4.dist-info/DESCRIPTION.rst
django_smtp_ntlm_backend-0.0.4.dist-info/METADATA
django_smtp_ntlm_backend-0.0.4.dist-info/RECORD
django_smtp_ntlm_backend-0.0.4.dist-info/WHEEL
django_smtp_ntlm_backend-0.0.4.dist-info/metadata.json
django_smtp_ntlm_backend-0.0.4.dist-info/top_level.txt
