Metadata-Version: 2.0
Name: django-smtp-ntlm-backend
Version: 0.0.4
Summary: A Django email backend for SMTP servers with NTLM authentication
Home-page: https://github.com/shadiakiki1986/django-smtp-ntlm-backend/
Author: Shadi Akiki
Author-email: shadiakiki1986@gmail.com
License: GNU Lesser GPL
Download-URL: https://github.com/shadiakiki1986/django-smtp-ntlm-backend/archive/master.zip
Platform: Posix
Platform: MacOS X
Platform: Windows
Classifier: Development Status :: 4 - Beta
Classifier: Intended Audience :: Developers
Classifier: License :: OSI Approved :: MIT License
Classifier: Operating System :: OS Independent
Classifier: Programming Language :: Python
Classifier: Programming Language :: Python :: 2.6
Classifier: Programming Language :: Python :: 2.7
Classifier: Programming Language :: Python :: 3.2
Classifier: Programming Language :: Python :: 3.3
Classifier: Programming Language :: Python :: 3.4
Classifier: Topic :: Software Development :: Libraries :: Python Modules
Classifier: Framework :: Django
Requires-Dist: Django (>=1.5)
Requires-Dist: shadiakiki1986-python-ntlm3 (>=1.0.5-dev)
